ChiMera/__init__.py
ChiMera/chimera_core.py
ChiMera/dependencies/__init__.py
ChiMera/dependencies/all_metabo_paths/__init__.py
ChiMera/dependencies/all_metabo_paths/carbohydrate_metabolism.json
ChiMera/dependencies/all_metabo_paths/central_carbon_metabolism_final.json
ChiMera/dependencies/all_metabo_paths/central_metabolism.json
ChiMera/dependencies/all_metabo_paths/fatty_acid_beta_oxidation.json
ChiMera/dependencies/all_metabo_paths/fatty_acid_biosynthesis_saturated.json
ChiMera/dependencies/all_metabo_paths/glycolysis_TCA_PPP.json
ChiMera/dependencies/all_metabo_paths/inositol_retinol_metabolism.json
ChiMera/dependencies/all_metabo_paths/nucleotide_metabolism.json
ChiMera/dependencies/all_metabo_paths/partial_amino_acid metabolism.json
ChiMera/dependencies/all_metabo_paths/tryptophan_metabolism.json
ChiMera/tools/__init__.py
ChiMera/tools/path_harvest.py
ChiMera/tools/silencer.py
ChiMera_gsmr-2.0.0.dist-info/LICENSE
ChiMera_gsmr-2.0.0.dist-info/METADATA
ChiMera_gsmr-2.0.0.dist-info/WHEEL
ChiMera_gsmr-2.0.0.dist-info/top_level.txt
ChiMera_gsmr-2.0.0.dist-info/RECORD
