Metadata-Version: 2.1
Name: ChiMera-gsmr
Version: 2.0.0
Summary: ChiMera: An easy-to-use pipeline for Genome-based Metabolic Network reconstruction, evaluation, and visualization.
Home-page: https://github.com/tamascogustavo/chimera
Author: Tamasco Gustavo
Author-email: tamascogustavo@gmail.com
License: gpl3
Project-URL: Bug Tracker, https://github.com/tamascogustavo/chimera/issues
Classifier: Programming Language :: Python :: 3
Classifier: Operating System :: POSIX :: Linux
Classifier: Operating System :: MacOS :: MacOS X
Requires-Python: ~=3.6
License-File: LICENSE
Requires-Dist: carveme
Requires-Dist: MarkupSafe (~=2.0.1)
Requires-Dist: diamond
Requires-Dist: cobra
Requires-Dist: escher (~=1.7.3)
Requires-Dist: psamm
Requires-Dist: ray
Requires-Dist: seaborn
Requires-Dist: matplotlib
Requires-Dist: bs4
Requires-Dist: argparse
Requires-Dist: requests
Requires-Dist: numpy
Requires-Dist: plotly
Requires-Dist: plotly-express
